[
    {
        "module": "Module 1",
        "topics": [
            "Introduction",
            "Definition",
            "Characteristics",
            "Functions",
            "Classification of Composites Based on Structure and Matrix",
            "Smart Composites",
            "Industrial Applications",
            "Interfaces: Wettability and Bonding Interface in Composites, Types of Bonding at Interface",
            "Fibers: Introduction",
            "Types of Fibers",
            "Natural Fibers",
            "Glass Fiber Fabrication",
            "Structure",
            "Properties and Applications",
            "Boron Fiber Fabrication",
            "Structure",
            "Properties and Applications"
        ],
        "rejected_topics": null,
        "status": "verified"
    },
    {
        "module": "Module 2",
        "topics": [
            "Thermoset",
            "Thermoplastic and Elastomeric Polymers",
            "Properties",
            "Characteristics and Applications as Matrix Materials",
            "Processing of Polymer Matrix Composites: Hand Layup Methods and Spray Layup Method",
            "Moulding Methods: Pressure Bagging and Bag Moulding Methods",
            "Autoclave-based Processing with Prepregs",
            "Pultrusion and Filament Winding Process"
        ],
        "rejected_topics": null,
        "status": "verified"
    },
    {
        "module": "Module 3",
        "topics": [
            "Metal Matrix Composites (MMC): Classification of Metals",
            "Intermetallics",
            "Alloys and Their Potential Role as Matrices in Composites",
            "Properties",
            "Characteristics and Applications of Metals as Matrix Materials",
            "Production Techniques: Powder Metallurgy",
            "Diffusion Bonding",
            "Melt Stirring",
            "Squeeze Casting",
            "Liquid Infiltration under Pressure",
            "In Situ Process"
        ],
        "rejected_topics": null,
        "status": "verified"
    },
    {
        "module": "Module 4",
        "topics": [
            "Ceramic Matrix Composites (CMC): Classification of Ceramics and Their Potential Role as Matrices",
            "Properties",
            "Characteristics and Applications of CMC",
            "Conventional Production Techniques: Cold Pressing and Sintering",
            "Hot Pressing",
            "Reaction Bonding",
            "Liquid Infiltration",
            "Pultrusion",
            "Lanxide Process",
            "In Situ Chemical Technique",
            "Sol-Gel Technique"
        ],
        "rejected_topics": null,
        "status": "verified"
    }
]