[
    {
        "module": "Module 1",
        "topics": [
            "Soil Science and Sensors",
            "Soil Science: Fundamental Definitions and Relationships",
            "Properties of Soil: Index Properties of Soil",
            "Engineering Properties of Soil",
            "Physical Properties of Soil",
            "Permeability and Seepage Analysis",
            "Mohr's Circle of Stress",
            "Necessity of Instrumentation and Control for Agriculture",
            "Sensors and Transducers: Definitions",
            "Introduction to Sonic Anemometers",
            "Hygrometers",
            "Thermocouples",
            "Close Path Gas Analysers",
            "Introduction to Various Biosensors"
        ]
    },
    {
        "module": "Module 2",
        "topics": [
            "Instrumentation in Industrial Continuous and Batch Processes",
            "Idea about Continuous and Batch Processes",
            "Flow Diagram of Sugar Plant, Sensors and Instrumentation Set Up",
            "Flow Diagram of Fermenter, Sensors and Instrumentation Set Up",
            "Flow Diagram of Dairy Industry and Instrumentation Set Up",
            "Juice Extraction Control Process and Instrumentation Set Up",
            "Oil Extraction Plant and Instrumentation Set Up",
            "Pesticides Manufacturing Process and Control"
        ]
    },
    {
        "module": "Module 3",
        "topics": [
            "Instrumentation in Irrigation",
            "Necessity of Irrigation in Agriculture",
            "Evapotranspiration and Its Measurement Methods",
            "Irrigation Methods: Overhead",
            "Centre Pivot",
            "Lateral Move",
            "Micro Irrigation Systems and Comparison of Different Irrigation Systems",
            "Soil Moisture Measurement Methods: Resistance-based Method",
            "Voltage-based Method",
            "Thermal-based Method",
            "Water Distribution and Management Control",
            "Auto Drip and Sprinkler Irrigation Systems",
            "Irrigation Canal Management Systems: Upstream and Downstream Control Concept",
            "Introduction to SCADA",
            "Applications of SCADA in Agriculture"
        ]
    },
    {
        "module": "Module 4",
        "topics": [
            "Greenhouse Parameters and Instrumentation",
            "Greenhouse Effect",
            "Concept and Construction of Green Houses",
            "Ventilation",
            "Cooling and Heating",
            "Wind Speed",
            "Temperature and Humidity",
            "Soil Moisture",
            "Rain Gauge",
            "Carbon Dioxide Enrichment Measurement and Control",
            "Implementation of Hydraulic, Pneumatic and Electronics Control Circuits in Harvesters",
            "Cotton Pickers",
            "Tractor",
            "Classification of Pumps: Pump Characteristics",
            "Pump Selection and Installation"
        ]
    }
]