[
  {
    "module": "Module 1",
    "topics": [
      "Introduction",
      "review of fundamentals of kinematics",
      "analysis and synthesis",
      "terminology, definitions and assumptions",
      "planar, spherical and spatial mechanisms‟ mobility",
      "classification of mechanisms",
      "kinematic Inversion",
      "Grashoff`s law Position and displacement",
      "complex algebra solutions of planar vector equations",
      "coupler curve generation velocity",
      "analytical methods",
      "vector method",
      "complex algebra methods",
      "Freudenstein‟s theorem"
    ],
    "rejected_topics": null,
    "status": "verified"
  },
  {
    "module": "Module 2",
    "topics": [
      "Planar complex mechanisms",
      "kinematic analysis",
      "low degree complexity and high degree complexity, Hall and Ault`s auxiliary point method",
      "Goodman‟s indirect method for low degree of complexity mechanisms Acceleration",
      "analytical methods",
      "Chase solution",
      "Instant centre of acceleration. Euler-Savory equation",
      "Bobillier construction"
    ],
    "rejected_topics": null,
    "status": "verified"
  },
  {
    "module": "Module 3",
    "topics": [
      "Synthesis of mechanisms",
      "Type",
      "number and dimensional synthesis - function generation - two position synthesis of slider crank and crankrocker mechanisms with optimum transmission angle - three position synthesis - structural error - Chebychev spacing - Cognate linkages - Robert-Chebychev theorem - Block‟s method of synthesis",
      "Freudenstein‟s equation"
    ],
    "rejected_topics": null,
    "status": "verified"
  },
  {
    "module": "Module 4",
    "topics": [
      "Kinematic analysis of spatial revolute-Spherical-Spherical-Revolute mechanism",
      "Denavit- Hartenberg parameters",
      "forward and inverse kinematics of robotic manipulators"
    ],
    "rejected_topics": null,
    "status": "verified"
  }
]