[
    {
        "module": "Module 1",
        "topics": [
            "Introduction, Role of Marine Engineers",
            "Need of Knowledge on Marine Engineering for a Naval Architect",
            "Joint Responsibilities of Marine Engineer and Naval Architect During Design, Survey and Repair of Vessels",
            "IMO/MARPOL Regulations, Engine Room Layout, Layout of Main and Auxiliary Machinery in Engine Rooms of Different Ships"
        ],
        "rejected_topics": null,
        "status": "verified"
    },
    {
        "module": "Module 2",
        "topics": [
            "Types and Application of Main Propulsion System, Main Engine - Diesel Engine, Steam Turbine, Electric Propulsion",
            "Diesel Engine Components",
            "Scavenging",
            "Supercharging",
            "Starting and Reversing",
            "Hazards and Maintenance of Diesel Engine",
            "Reduction Gearing, Auxiliary Machinery, Requirement of Auxiliary Machinery, List and Functions",
            "Differentiation of Auxiliary Engines from Main Engines",
            "Working Principle and Onboard Applications of Different Types of Marine Air Compressors, Marine Pumps, Marine Boilers, Purifiers, Marine Valves, Heat Exchangers, Oil Water Separators, Incinerators, Sewage Treatment Plant, Fresh Water Generator"
        ],
        "rejected_topics": null,
        "status": "verified"
    },
    {
        "module": "Module 3",
        "topics": [
            "Marine Piping and Major Marine Systems, Piping Arrangement for Steam",
            "Bilge",
            "Ballast and Oil Fuel Systems",
            "Lube Oil and Cooling System with Various Fittings",
            "Domestic Fresh Water and Sea Water Hydrophore System, Deck Machinery, Deck Cranes",
            "Windlasses",
            "Mooring Winches",
            "Anchors and Anchor Chains",
            "Davits and Lifeboats Lowering Mechanism",
            "Cargo Handling Equipment"
        ],
        "rejected_topics": null,
        "status": "verified"
    },
    {
        "module": "Module 4",
        "topics": [
            "Shafting and Propellers, Stern Tubes and Glands, Oil Lubricated Stern Tubes",
            "Shaft Seals",
            "Shaft Alignment",
            "Thrust Block",
            "Propeller Types and Construction Details",
            "Maintenance and Operation of Marine Propellers, Steering Gear, Operation and Constructional Details of Various Types of Steering Machinery, Ship Stabilizers, Types, Operations of Different Types of Passive and Active Ship Stabilizing Systems"
        ],
        "rejected_topics": null,
        "status": "verified"
    }
]