[
    {
        "module": "Module 1",
        "topics": [
            "Review of Semiconductor Physics - Equilibrium and Steady State Conditions",
            "Concept of Effective Mass and Fermi Level",
            "Density of States & Effective Density of States",
            "Equilibrium Concentration of Electrons and Holes. Excess Carriers in Semiconductors - Generation and Recombination Mechanisms of Excess Carriers",
            "Quasi-Fermi Levels. Carrier Transport in Semiconductors - Drift",
            "Conductivity and Mobility",
            "Variation of Mobility with Temperature and Doping",
            "Hall Effect"
        ],
        "rejected_topics": null,
        "status": "verified"
    },
    {
        "module": "Module 2",
        "topics": [
            "Contact Potential",
            "Electric Field",
            "Potential and Charge Distribution at the Junction",
            "Biasing and Energy Band Diagrams",
            "Ideal Diode Equation. Bipolar Junction Transistor - Working",
            "Transistor Action",
            "Base Width Modulation",
            "Current Components in a BJT"
        ],
        "rejected_topics": null,
        "status": "verified"
    },
    {
        "module": "Module 3",
        "topics": [
            "Ideal MOS Capacitor - Band Diagrams at Equilibrium",
            "Accumulation",
            "Depletion and Inversion",
            "Surface Potential",
            "CV Characteristics",
            "Effects of Real Surfaces",
            "Threshold Voltage",
            "Body Effect. MOSFET - Structure",
            "Working",
            "Types",
            "Drain Current Equation of Enhancement Type MOSFET (Derivation) - Linear and Saturation Region",
            "Drain Characteristics",
            "Transfer Characteristics"
        ],
        "rejected_topics": null,
        "status": "verified"
    },
    {
        "module": "Module 4",
        "topics": [
            "MOSFET Scaling - Need for Scaling",
            "Constant Voltage Scaling and Constant Field Scaling. Sub-threshold Conduction in MOS. Short Channel Effects in MOSFETs - Channel Length Modulation",
            "Drain Induced Barrier Lowering",
            "Velocity Saturation",
            "Threshold Voltage Variations and Hot Carrier Effects. FinFET - Structure",
            "Operation and Advantages"
        ],
        "rejected_topics": null,
        "status": "verified"
    }
]