[
    {
        "module": "Module 1",
        "topics": [
            "Linear Systems of Equations",
            "Solution by Gauss Elimination",
            "Row Echelon Form and Rank of a Matrix",
            "Fundamental Theorem for Linear Systems - Homogeneous and Non-Homogeneous",
            "Eigenvalues and Eigenvectors of Matrices",
            "Diagonalization of Matrices"
        ],
        "rejected_topics": null,
        "status": "verified"
    },
    {
        "module": "Module 2",
        "topics": [
            "Transition Matrix"
        ],
        "rejected_topics": null,
        "status": "verified"
    },
    {
        "module": "Module 3",
        "topics": [
            "Vector Length and Unit Vector",
            "Dot Product and Angle Between Two Vectors",
            "The Cauchy-Schwarz Inequality",
            "Inner Product",
            "Examples in Rn and M2x2",
            "Properties of Inner Products",
            "Definitions of Length",
            "Distance and Angle",
            "Orthogonal Projections in Inner Product Spaces",
            "Orthogonal and Orthonormal Sets",
            "Orthogonal and Orthonormal Basis",
            "Gram-Schmidt Orthonormalization Process",
            "The Least Squares Problem",
            "Projection onto a Subspace",
            "Solving the Least Squares Problems"
        ],
        "rejected_topics": null,
        "status": "verified"
    },
    {
        "module": "Module 4",
        "topics": [
            "Linear Transformations",
            "Properties of Linear Transformations",
            "Linear Transformation Given by a Matrix",
            "Rotation in R2",
            "Projection in R3",
            "Kernel of a Linear Transformation and Its Basis",
            "Range of a Linear Transformation and Its Basis",
            "Rank and Nullity of a Linear Transformation",
            "Sum of Rank and Nullity",
            "Matrices for Linear Transformations"
        ],
        "rejected_topics": null,
        "status": "verified"
    }
]