{
  "id": "pcmel609-me-s7",
  "code": "PCMEL609",
  "name": "THERMAL ENGINEERING LAB-2",
  "branchId": "me",
  "semester": 7,
  "modules": [
    {
      "id": "mExperiment 2",
      "title": "Module Experiment 2",
      "topics": [
        {
          "id": "tExperiment 2_1",
          "title": "Familiarisation of various systems and subsystems of petrol engine / MPFI engine",
          "content": "",
          "pyqs": []
        },
        {
          "id": "tExperiment 2_2",
          "title": "Familiarisation of various systems and subsystems of Diesel engine / Turbocharged engine",
          "content": "",
          "pyqs": []
        },
        {
          "id": "tExperiment 2_3",
          "title": "Performance test on petrol engines / MPFI engine",
          "content": "",
          "pyqs": []
        },
        {
          "id": "tExperiment 2_4",
          "title": "Performance test on Diesel engines / Turbocharged engine",
          "content": "",
          "pyqs": []
        },
        {
          "id": "tExperiment 2_5",
          "title": "Heat Balance test on petrol/Diesel engines",
          "content": "",
          "pyqs": []
        },
        {
          "id": "tExperiment 2_6",
          "title": "Determination of volumetric efficiency and Air-fuel ratio of IC engines",
          "content": "",
          "pyqs": []
        },
        {
          "id": "tExperiment 2_7",
          "title": "Cooling curve of IC engines",
          "content": "",
          "pyqs": []
        },
        {
          "id": "tExperiment 2_8",
          "title": "Valve timing diagram of IC engines",
          "content": "",
          "pyqs": []
        },
        {
          "id": "tExperiment 2_9",
          "title": "Economic speed test on IC engines",
          "content": "",
          "pyqs": []
        },
        {
          "id": "tExperiment 2_10",
          "title": "Retardation test on IC engines",
          "content": "",
          "pyqs": []
        },
        {
          "id": "tExperiment 2_11",
          "title": "Morse test on petrol engine",
          "content": "",
          "pyqs": []
        },
        {
          "id": "tExperiment 2_12",
          "title": "Analysis of automobile exhaust gas and flue gas using exhaust gas analyser",
          "content": "",
          "pyqs": []
        },
        {
          "id": "tExperiment 2_13",
          "title": "Performance test on reciprocating compressor",
          "content": "",
          "pyqs": []
        },
        {
          "id": "tExperiment 2_14",
          "title": "Performance test on rotary compressor/blower",
          "content": "",
          "pyqs": []
        },
        {
          "id": "tExperiment 2_15",
          "title": "Study and performance test on refrigeration (Refrigeration Test rig)",
          "content": "",
          "pyqs": []
        },
        {
          "id": "tExperiment 2_16",
          "title": "Study and performance test on air conditioning equipment (Air Conditioning test rig)",
          "content": "",
          "pyqs": []
        }
      ]
    }
  ]
}
