[
  {
    "module": "Module 1",
    "topics": [
      "Basic concepts of plant layout and design including a basic understanding of equipment layout, ventilation",
      "Design consideration for the location of food plants. The material of Construction for food processing equipment",
      "Specifications of processing equipment and accessories",
      "provision for waste disposal, and safety arrangements aspects of plant layout and design",
      "Symbols used for food plant design and layout"
    ],
    "rejected_topics": null,
    "status": "verified"
  },
  {
    "module": "Module 2",
    "topics": [
      "Introduction to feasibility study and analysis Layout and design aspects of pilot and semi-commercial food processing plants",
      "Reference to the design of bakery and biscuit, fruits, vegetable, and beverage processing, and dairy industries",
      "Hygienic Design of Food Plants",
      "specific FSSAI requirements in food plant layout and design"
    ],
    "rejected_topics": null,
    "status": "verified"
  },
  {
    "module": "Module 3",
    "topics": [
      "Application of Program Evaluation and Review Technique (PERT) and Critical Path Method (CPM) in project planning and monitoring",
      "application of ISO, HACCP in food plant, Experimentation in Pilot Plant"
    ],
    "rejected_topics": null,
    "status": "verified"
  },
  {
    "module": "Module 4",
    "topics": [
      "Optimum economic design, Feasibility Survey",
      "Preparation of flow sheets for material movement and utility consumption in food plants",
      "Cost estimation for a Food Plant",
      "Scale-up, Food processing enterprise, Plant operation"
    ],
    "rejected_topics": null,
    "status": "verified"
  }
]