[
    {
        "module": "Module 1",
        "topics": [
            "Cryptography",
            "Concepts and Techniques-Introduction",
            "plaintext and cipher text",
            "substitution techniques",
            "transposition techniques",
            "encryption and decryption",
            "symmetric and asymmetric key cryptography. Introduction to block-chain - basic ideas behind blockchain",
            "generic elements of a blockchain. Types -private",
            "public",
            "hybrid blockchain. Applications of Blockchain in E-Governance",
            "Land Registration",
            "Medical Information Systems",
            "and others. Benefits & Limitations of blockchain"
        ],
        "rejected_topics": null,
        "status": "verified"
    },
    {
        "module": "Module 2",
        "topics": [
            "Blockchain",
            "Versions",
            "variants",
            "usecases",
            "life-usecases of blockchain",
            "Blockchain vs shared database. The real need for mining - Consensus - definition",
            "types",
            "consensus in blockchain",
            "Byzantine Generals Problem",
            "and Consensus as a distributed coordination problem. Decentralization - Decentralization using blockchain",
            "Methods of decentralization",
            "Routes to decentralization",
            "Blockchain and full ecosystem decentralization"
        ],
        "rejected_topics": null,
        "status": "verified"
    },
    {
        "module": "Module 3",
        "topics": [
            "Introduction to crypto-currency",
            "definition",
            "types",
            "applications. Introduction to Bitcoins",
            "Definition",
            "Bitcoin Digital Keys & Addresses",
            "Transactions",
            "Limitations of Bitcoins. Introduction to Blockchain platforms",
            "Ethereum",
            "Hyperledger",
            "IOTA",
            "Multichain",
            "Bigchain etc. Advantages & disadvantages"
        ],
        "rejected_topics": null,
        "status": "verified"
    },
    {
        "module": "Module 4",
        "topics": [
            "Smart Contracts - Definition",
            "Smart contract templates",
            "Oracles",
            "Types of oracles",
            "Deploying smart contracts. Ethereum - The Ethereum network. Components of the Ethereum ecosystem - Keys and addresses",
            "Accounts",
            "Transactions and messages"
        ],
        "rejected_topics": null,
        "status": "verified"
    }
]