[
    {
        "module": "Module 1",
        "topics": [
            "Need of Compiler",
            "Analysis of the Source Program",
            "Phases of a Compiler",
            "Grouping of Phases",
            "Compiler Writing Tools",
            "Cross Compiler",
            "Lexical Analyser: Role of Lexical Analyzer",
            "Review of Finite Automata",
            "Design of Lexical Analyser Using DFAs",
            "Specification of Tokens Using Regular Expressions"
        ],
        "rejected_topics": null,
        "status": "verified"
    },
    {
        "module": "Module 2",
        "topics": [
            "Review of Context-Free Grammars",
            "Parse Trees",
            "Ambiguous Grammars",
            "Top-Down Parsing: Recursive Descent Parser",
            "Predictive Parser - LL(1)",
            "Bottom-Up Parsing: LR(0) Parser",
            "SLR(1) Parser",
            "CLR(1) Parser",
            "LALR Parser"
        ],
        "rejected_topics": null,
        "status": "verified"
    },
    {
        "module": "Module 3",
        "topics": [
            "Syntax-Directed Definitions: S-Attributed Definitions",
            "L-Attributed Definitions",
            "Bottom-Up Evaluation of S-Attributed Definitions",
            "Top-Down Translation",
            "Bottom-Up Evaluation of Inherited Attributes",
            "Intermediate Code Generation (ICG): Need of ICG",
            "Different Representations of Intermediate Code",
            "Intermediate Code for Assignment Statement"
        ],
        "rejected_topics": null,
        "status": "verified"
    },
    {
        "module": "Module 4",
        "topics": [
            "Principal Sources of Optimization",
            "Optimization of Basic Blocks",
            "Code Generation: Issues in the Design of a Code Generator",
            "A Simple Code Generator"
        ],
        "rejected_topics": null,
        "status": "verified"
    }
]