[
    {
        "module": "Module 1",
        "topics": [
            "Traditional Economic Theory and Assumptions",
            "Limits of Rationality",
            "Bounded Rationality Heuristics and Bias: Representativeness",
            "Biases Resulting from Representativeness",
            "Confirmation Bias",
            "Anchoring",
            "Availability",
            "Affect",
            "Overconfidence",
            "Exponential Growth Bias",
            "Other Biases"
        ],
        "rejected_topics": null,
        "status": "verified"
    },
    {
        "module": "Module 2",
        "topics": [
            "Expected Utility",
            "Risk Aversion",
            "Reference Dependence and Prospect Theory",
            "Insurance",
            "Tax Evasion and Time Preference: Hyperbolic Discounting",
            "Loss Aversion and Sequences",
            "Time and Risk",
            "Environmental Economics and Inter-Generational Discount Factor"
        ],
        "rejected_topics": null,
        "status": "verified"
    },
    {
        "module": "Module 3",
        "topics": [
            "Behavioural Insights for Public Policy: Role of Government in Shaping Behaviour",
            "Designing Good Institutions: The Tragedy of the Commons",
            "Matching Markets",
            "Behavioural Economics and Institution Design: Behavioural Insights for Public Policy",
            "Nudge and Behaviour Change: Fairness and Distributional Effects",
            "Ethical Considerations in Behavioural Public Policy"
        ],
        "rejected_topics": null,
        "status": "verified"
    },
    {
        "module": "Module 4",
        "topics": [
            "Information Asymmetry",
            "Behavioural Interventions for Promoting Healthy Behaviours",
            "Health and Happiness",
            "Measuring the Value of Treatment",
            "Improving the Remembered Utility of Treatment",
            "Behavioural Economics and Education Policy: The Role of Social Norms in Promoting Education",
            "Role of Gender and Economic Outcomes",
            "Happiness and Utility: Remembered Utility",
            "Projection Bias",
            "Present Bias",
            "Pre-Commitment"
        ],
        "rejected_topics": null,
        "status": "verified"
    }
]